syncP/__init__.py
syncP/__main__.py
syncP/client.py
syncP/host.py
syncP/mpv.py
syncP/player.py
syncP/testmpv.py
syncP/media/vid.mp4
syncP-1.0.4.dist-info/LICENSE
syncP-1.0.4.dist-info/METADATA
syncP-1.0.4.dist-info/WHEEL
syncP-1.0.4.dist-info/entry_points.txt
syncP-1.0.4.dist-info/top_level.txt
syncP-1.0.4.dist-info/RECORD
