Metadata-Version: 2.1
Name: syncP
Version: 1.0.4
Summary: A mpv syncing tool among clients and host for local media files
Home-page: https://github.com/lawRathod/syncP
Author: Prateek Rathod
Author-email: prateekrathod.dev@gmail.com
License: MIT
Download-URL: https://github.com/lawRathod/syncP
Platform: UNKNOWN
Classifier: License :: OSI Approved :: MIT License
Classifier: Programming Language :: Python :: 2.7
Classifier: Programming Language :: Python :: 3
Classifier: Programming Language :: Python :: 3.7
Requires-Python: >=3.4
